{
  "gitSyncId": "68600ba97c31ed49d151bad2_120a2abb-7f2c-4771-8930-17914acf48fd",
  "id": "Reporting_AuthManager.login",
  "pluginId": "js-plugin",
  "pluginType": "JS",
  "unpublishedAction": {
    "actionConfiguration": {
      "encodeParamsToggle": true,
      "jsArguments": [],
      "paginationType": "NONE",
      "timeoutInMillisecond": 10000
    },
    "collectionId": "Reporting_AuthManager",
    "confirmBeforeExecute": false,
    "datasource": {
      "isAutoGenerated": false,
      "name": "UNUSED_DATASOURCE",
      "pluginId": "js-plugin"
    },
    "dynamicBindingPathList": [
      {
        "key": "body"
      }
    ],
    "fullyQualifiedName": "AuthManager.login",
    "name": "login",
    "pageId": "Reporting",
    "runBehaviour": "MANUAL",
    "userSetOnLoad": false
  }
}